LICENSE
MANIFEST.in
README.md
pyproject.toml
Sift.egg-info/PKG-INFO
Sift.egg-info/SOURCES.txt
Sift.egg-info/dependency_links.txt
Sift.egg-info/requires.txt
Sift.egg-info/top_level.txt
sift/__init__.py
sift/client.py
sift/constants.py
sift/exceptions.py
sift/utils.py
sift/version.py