Metadata-Version: 2.1
Name: Sift
Version: 6.0.0
Summary: Python bindings for Sift Science's API
Author-email: Sift Science <support@siftscience.com>
License: The MIT License
Project-URL: Source, https://github.com/SiftScience/sift-python
Project-URL: Changelog, https://github.com/SiftScience/sift-python/blob/master/CHANGES.md
Keywords: sift,sift-python
Classifier: Development Status :: 5 - Production/Stable
Classifier: Intended Audience :: Developers
Classifier: Topic :: Software Development :: Libraries :: Python Modules
Classifier: Programming Language :: Python :: 3
Classifier: Programming Language :: Python :: 3 :: Only
Classifier: Programming Language :: Python :: 3.8
Classifier: Programming Language :: Python :: 3.9
Classifier: Programming Language :: Python :: 3.10
Classifier: Programming Language :: Python :: 3.11
Classifier: Programming Language :: Python :: 3.12
Classifier: Programming Language :: Python :: 3.13
Classifier: Operating System :: OS Independent
Classifier: Typing :: Typed
Classifier: License :: OSI Approved :: MIT License
Requires-Python: >=3.8
License-File: LICENSE
